Metadata-Version: 2.4
Name: cdsodatacli
Version: 2025.11.12
Summary: OData client for Copernicus Data Space catalog
Author: Antoine Grouazel, Jean-Renaud Miadana
License: MIT
Keywords: Odata,copernicus-data-space,api
Classifier: Development Status :: 3 - Alpha
Classifier: Intended Audience :: Developers
Classifier: Operating System :: OS Independent
Classifier: Topic :: Software Development :: Libraries :: Python Modules
Classifier: License :: OSI Approved :: MIT License
Classifier: Programming Language :: Python :: 3
Classifier: Programming Language :: Python :: 3.9
License-File: LICENSE
Requires-Dist: geopandas
Requires-Dist: geodatasets
Requires-Dist: numpy
Requires-Dist: requests
Requires-Dist: shapely
Requires-Dist: tqdm
Requires-Dist: pyyaml
Requires-Dist: cartopy
Requires-Dist: python-dotenv
Provides-Extra: dev
Requires-Dist: pre-commit; extra == "dev"
Requires-Dist: pytest; extra == "dev"
Requires-Dist: pytest-cov; extra == "dev"
Requires-Dist: pytest-env; extra == "dev"
Requires-Dist: pytest-xdist; extra == "dev"
Requires-Dist: pytest-timeout; extra == "dev"
Requires-Dist: ruff>=0.8.0; extra == "dev"
Requires-Dist: sphinx; extra == "dev"
Requires-Dist: sphinx_autosummary_accessors; extra == "dev"
Dynamic: license-file
